insightpy/__init__.py
insightpy/sv_public.py
insightpy/cli/__init__.py
insightpy/cli/profiler_cli.py
insightpy/core/__init__.py
insightpy/core/utils.py
insightpy/core/analyzer/__init__.py
insightpy/core/analyzer/data_summary.py
insightpy/core/analyzer/feature_importance.py
insightpy/core/analyzer/interaction_analizer.py
insightpy/core/analyzer/outlier_analyzer.py
insightpy/core/analyzer/missing_value/__init__.py
insightpy/core/analyzer/missing_value/missing_data_analyzer.py
insightpy/core/analyzer/missing_value/missing_values.py
insightpy/core/dataset/__init__.py
insightpy/core/dataset/data_loader.py
insightpy/core/dataset/dataset.py
insightpy/core/feature/__init__.py
insightpy/core/feature/base_feature.py
insightpy/core/feature/base_target.py
insightpy/core/feature/categorical_feature.py
insightpy/core/feature/categorical_target_feature.py
insightpy/core/feature/numerical_feature.py
insightpy/core/feature/numerical_target_feature.py
insightpy/core/profiler/__init__.py
insightpy/core/profiler/profiler.py
insightpy/plot/__init__.py
insightpy/plot/correlation_plots.py
insightpy/plot/histograms.py
insightpy/plot/scatter_plots.py
insightpy/ui/__init__.py
insightpy/ui/web_ui.py
insightpy/utils/__init__.py
insightpy/utils/file_utils.py
insightpy-0.0.4.dist-info/LICENSE
insightpy-0.0.4.dist-info/METADATA
insightpy-0.0.4.dist-info/WHEEL
insightpy-0.0.4.dist-info/entry_points.txt
insightpy-0.0.4.dist-info/top_level.txt
insightpy-0.0.4.dist-info/RECORD
